{
  "commits": [
    {
      "hash": "f8f0f4f5ca75e978620bef6dc4e2a8de4d250fb6",
      "date": "2026-04-27 09:31:52 +0800",
      "message": "feat(quant): complete quant system guide with roadmap and resources"
    },
    {
      "hash": "78cc41ca9ea226bf329e3a036632256001e894c3",
      "date": "2026-04-25 20:36:16 +0800",
      "message": "feat(content): add visibility controls for posts"
    },
    {
      "hash": "73215ae37f48c273a0ce2092df8c6b34533c21f9",
      "date": "2026-04-25 11:46:06 +0800",
      "message": "chore(build): clean dist sections and refresh content metadata"
    },
    {
      "hash": "d550f10baf58ef908b009ffcf5c1e465d36f06b7",
      "date": "2026-04-24 17:14:03 +0800",
      "message": "feat(analytics): add ip profile sync and dashboard SQL scaffold"
    },
    {
      "hash": "b127fc3cfd274c260f7ac17acedf3f2e19a74659",
      "date": "2026-04-24 16:39:36 +0800",
      "message": "refactor(home): align tags and archive navigation layout"
    },
    {
      "hash": "cd5fcbc9ead1b1bb6e1e3110ab53b867a84d977e",
      "date": "2026-04-24 13:21:03 +0800",
      "message": "feat: dashboard theme lock, stats merge, security & admin surfaces"
    },
    {
      "hash": "39a27a8029b40d016348b3e8106fabe9364afa62",
      "date": "2026-04-24 09:26:57 +0800",
      "message": "feat: visitor insights, analytics, and visit logging updates"
    },
    {
      "hash": "fccd8454f6c7c49d08cf8a3c5ffd60980719dee9",
      "date": "2026-04-23 23:20:38 +0800",
      "message": "refactor(statistics): polish labels and table scrollbar style"
    },
    {
      "hash": "4926fdaae5c1954a9dc093aadaacc3ee60488aaf",
      "date": "2026-04-23 17:42:27 +0800",
      "message": "refactor(statistics): remove inner scrollbars in dashboard panels"
    },
    {
      "hash": "f86d5c762223a2915b3c709249c1a3e15fdf8c09",
      "date": "2026-04-23 17:37:34 +0800",
      "message": "refactor(statistics): simplify rankings and remove tags route"
    }
  ],
  "timestamp": "2026-04-27T05:39:08.600Z"
}